asn1PERser/__init__.py
asn1PERser/logging_setup.py
asn1PERser/asn_definitions/__init__.py
asn1PERser/asn_definitions/assignment_def.py
asn1PERser/asn_definitions/character_and_word_set.py
asn1PERser/asn_definitions/common_def.py
asn1PERser/asn_definitions/constraint_def.py
asn1PERser/asn_definitions/lexical_items.py
asn1PERser/asn_definitions/module_def.py
asn1PERser/asn_definitions/type_def.py
asn1PERser/asn_definitions/value_def.py
asn1PERser/classes/__init__.py
asn1PERser/classes/module.py
asn1PERser/classes/parse_actions.py
asn1PERser/classes/data/__init__.py
asn1PERser/classes/data/builtin/BitStringType.py
asn1PERser/classes/data/builtin/BooleanType.py
asn1PERser/classes/data/builtin/ChoiceType.py
asn1PERser/classes/data/builtin/EnumeratedType.py
asn1PERser/classes/data/builtin/IntegerType.py
asn1PERser/classes/data/builtin/OctetStringType.py
asn1PERser/classes/data/builtin/SequenceOfType.py
asn1PERser/classes/data/builtin/SequenceType.py
asn1PERser/classes/data/builtin/UTF8String.py
asn1PERser/classes/data/builtin/__init__.py
asn1PERser/classes/templates/__init__.py
asn1PERser/classes/templates/creator.py
asn1PERser/classes/templates/files/BitStringType.txt
asn1PERser/classes/templates/files/BooleanType.txt
asn1PERser/classes/templates/files/ChoiceType.txt
asn1PERser/classes/templates/files/DefinedType.txt
asn1PERser/classes/templates/files/EnumeratedType.txt
asn1PERser/classes/templates/files/IntegerType.txt
asn1PERser/classes/templates/files/OctetStringType.txt
asn1PERser/classes/templates/files/SequenceOfType.txt
asn1PERser/classes/templates/files/SequenceType.txt
asn1PERser/classes/templates/files/__init__.py
asn1PERser/classes/templates/files/header.txt
asn1PERser/classes/templates/files/simple_value.txt
asn1PERser/classes/templates/files/type_type.txt
asn1PERser/classes/types/__init__.py
asn1PERser/classes/types/constraint.py
asn1PERser/classes/types/type.py
asn1PERser/classes/types/builtin/BitStringType.py
asn1PERser-0.4.3.dist-info/LICENSE
asn1PERser-0.4.3.dist-info/METADATA
asn1PERser-0.4.3.dist-info/WHEEL
asn1PERser-0.4.3.dist-info/top_level.txt
asn1PERser-0.4.3.dist-info/RECORD
