Metadata-Version: 2.1
Name: asn1PERser
Version: 0.4.3
Summary: Parse ASN.1 schemas into Python code and encode/decode them using PER encoder
Home-page: https://github.com/erupikus/asn1PERser
Author: Maciej Pikuła
Author-email: erupikus@gmail.com
Keywords: asn asn1 asn.1 PER decoder encoder
Classifier: Programming Language :: Python :: 2.7
Classifier: Programming Language :: Python :: 3.5
Classifier: Programming Language :: Python :: 3.6
Classifier: Programming Language :: Python :: 3.7
Classifier: License :: OSI Approved :: MIT License
Classifier: Operating System :: OS Independent
License-File: LICENSE
Requires-Dist: pyasn1 (>=0.4.7)
Requires-Dist: pyparsing (>=2.4.7)
Requires-Dist: Jinja2 (>=2.10.0)
Requires-Dist: future (>=0.18.2)
